MANIFEST.in
setup.cfg
setup.py
tw/__init__.py
tw.dynforms.egg-info/PKG-INFO
tw.dynforms.egg-info/SOURCES.txt
tw.dynforms.egg-info/dependency_links.txt
tw.dynforms.egg-info/entry_points.txt
tw.dynforms.egg-info/namespace_packages.txt
tw.dynforms.egg-info/not-zip-safe
tw.dynforms.egg-info/requires.txt
tw.dynforms.egg-info/top_level.txt
tw/dynforms/__init__.py
tw/dynforms/release.py
tw/dynforms/samples.py
tw/dynforms/widgets.py
tw/dynforms/static/ajax_lookup.js
tw/dynforms/static/del.png
tw/dynforms/static/dynforms.js
tw/dynforms/static/undo.png
tw/dynforms/templates/__init__.py
tw/dynforms/templates/__init__.pyc
tw/dynforms/templates/ajax_lookup.html
tw/dynforms/templates/filtering_grid.html
tw/dynforms/templates/growing_repeater.html
tw/dynforms/templates/growing_table_fieldset.html
tw/dynforms/templates/growing_table_form.html
tw/dynforms/templates/link_container.html
tw/dynforms/templates/other_select_field.html
tw/dynforms/templates/tr_fieldset.html